billiarded_chromedriver/__init__.py
billiarded_chromedriver/cdp.py
billiarded_chromedriver/devtool.py
billiarded_chromedriver/dprocess.py
billiarded_chromedriver/options.py
billiarded_chromedriver/patcher.py
billiarded_chromedriver/reactor.py
billiarded_chromedriver/webelement.py
billiarded_chromedriver-3.5.5.dist-info/LICENSE
billiarded_chromedriver-3.5.5.dist-info/METADATA
billiarded_chromedriver-3.5.5.dist-info/WHEEL
billiarded_chromedriver-3.5.5.dist-info/top_level.txt
billiarded_chromedriver-3.5.5.dist-info/RECORD
