Metadata-Version: 2.1
Name: billiarded-chromedriver
Version: 3.5.5
Summary: ('Fork of the undetected_chromedriver by ULTRAFUNKAMSTERDAM', 'Multiprocessing is replaced with billiard for using with celery', 'Source description:', 'Selenium.webdriver.Chrome replacement with compatiblity for Brave, and other Chromium based browsers.', 'Not triggered by CloudFlare/Imperva/hCaptcha and such.', 'NOTE: results may vary due to many factors. No guarantees are given, except for ongoing efforts in understanding detection algorithms.')
Home-page: https://github.com/coldwhiskeyman/billiarded-chromedriver
Author: coldwhiskeyman
Author-email: eldiablo5783@gmail.com
License: GPL-3.0
Classifier: License :: OSI Approved :: GNU General Public License v3 (GPLv3)
Classifier: Programming Language :: Python :: 3
Classifier: Programming Language :: Python :: 3.7
Classifier: Programming Language :: Python :: 3.8
Classifier: Programming Language :: Python :: 3.9
Classifier: Programming Language :: Python :: 3.10
Classifier: Programming Language :: Python :: 3.11
License-File: LICENSE
Requires-Dist: selenium >=4.9.0
Requires-Dist: requests
Requires-Dist: websockets
Requires-Dist: billiard
